cmapPy/__init__.py
cmapPy/clue_api_client/__init__.py
cmapPy/clue_api_client/cell_queries.py
cmapPy/clue_api_client/clue_api_client.py
cmapPy/clue_api_client/gene_queries.py
cmapPy/clue_api_client/macchiato_queries.py
cmapPy/clue_api_client/mock_clue_api_client.py
cmapPy/clue_api_client/pert_queries.py
cmapPy/clue_api_client/setup_logger.py
cmapPy/clue_api_client/tests/test_cell_queries.py
cmapPy/clue_api_client/tests/test_clue_api_client.py
cmapPy/clue_api_client/tests/test_gene_queries.py
cmapPy/clue_api_client/tests/test_genes_queries.py
cmapPy/clue_api_client/tests/test_macchiato_queries.py
cmapPy/clue_api_client/tests/test_mock_clue_api_client.py
cmapPy/clue_api_client/tests/test_pert_queries.py
cmapPy/math/__init__.py
cmapPy/math/agg_wt_avg.py
cmapPy/math/fast_corr.py
cmapPy/math/fast_cov.py
cmapPy/math/robust_zscore.py
cmapPy/math/tests/test_agg_wt_avg.py
cmapPy/math/tests/test_fast_corr.py
cmapPy/math/tests/test_fast_cov.py
cmapPy/math/tests/test_robust_zscore.py
cmapPy/pandasGEXpress/GCToo.py
cmapPy/pandasGEXpress/__init__.py
cmapPy/pandasGEXpress/concat.py
cmapPy/pandasGEXpress/concat_gctoo.py
cmapPy/pandasGEXpress/diff_gctoo.py
cmapPy/pandasGEXpress/gct2gctx.py
cmapPy/pandasGEXpress/gctx2gct.py
cmapPy/pandasGEXpress/mini_gctoo_for_testing.py
cmapPy/pandasGEXpress/parse.py
cmapPy/pandasGEXpress/parse_gct.py
cmapPy/pandasGEXpress/parse_gctx.py
cmapPy/pandasGEXpress/plategrp.py
cmapPy/pandasGEXpress/random_slice.py
cmapPy/pandasGEXpress/setup_GCToo_logger.py
cmapPy/pandasGEXpress/slice_gct.py
cmapPy/pandasGEXpress/slice_gctoo.py
cmapPy/pandasGEXpress/subset.py
cmapPy/pandasGEXpress/subset_gctoo.py
cmapPy/pandasGEXpress/write_gct.py
cmapPy/pandasGEXpress/write_gctx.py
cmapPy/pandasGEXpress/tests/__init__.py
cmapPy/pandasGEXpress/tests/test_GCToo.py
cmapPy/pandasGEXpress/tests/test_concat.py
cmapPy/pandasGEXpress/tests/test_concat_gctoo.py
cmapPy/pandasGEXpress/tests/test_diff_gctoo.py
cmapPy-4.0.1.dist-info/DESCRIPTION.rst
cmapPy-4.0.1.dist-info/METADATA
cmapPy-4.0.1.dist-info/RECORD
cmapPy-4.0.1.dist-info/WHEEL
cmapPy-4.0.1.dist-info/entry_points.txt
cmapPy-4.0.1.dist-info/metadata.json
cmapPy-4.0.1.dist-info/top_level.txt
