Metadata-Version: 1.1
Name: cmapPy
Version: 4.0.1
Summary: Assorted tools for interacting with .gct, .gctx files and other Connectivity Map (Broad Institute) data/tools
Home-page: https://github.com/cmap/cmapPy
Author: Oana Enache
Author-email: oana@broadinstitute.org
License: BSD 3-clause
Keywords: gct gctx file-manipulation Connectivity Map CMap Broad Institute
Platform: UNKNOWN
Classifier: Development Status :: 5 - Production/Stable
Classifier: Intended Audience :: Science/Research
Classifier: Topic :: Scientific/Engineering :: Bio-Informatics
Classifier: License :: OSI Approved :: BSD License
Classifier: Programming Language :: Python :: 2
Classifier: Programming Language :: Python :: 2.7
Classifier: Programming Language :: Python :: 3.6
